Metadata-Version: 2.4
Name: embeddings-zh
Version: 0.0.7
Summary: Embeddings with Chatopera Synonyms for chatbot, RAG.
Home-page: https://github.com/chatopera/embeddings-zh
Author: Hai Liang Wang
Author-email: info@chatopera.com
License: Chunsong Public License, version 1.0
Keywords: embeddings,nlp
Classifier: Intended Audience :: Developers
Classifier: Operating System :: OS Independent
Classifier: Natural Language :: Chinese (Simplified)
Classifier: Natural Language :: Chinese (Traditional)
Classifier: Programming Language :: Python
Classifier: Programming Language :: Python :: 3
Classifier: Programming Language :: Python :: 3.11
License-File: LICENSE
Requires-Dist: synonyms>=3.25.1
Dynamic: author
Dynamic: author-email
Dynamic: classifier
Dynamic: description
Dynamic: home-page
Dynamic: keywords
Dynamic: license
Dynamic: license-file
Dynamic: requires-dist
Dynamic: summary
